fixclient/__init__.py
fixclient/async_client.py
fixclient/ca.py
fixclient/http_client/__init__.py
fixclient/http_client/aiohttp_client.py
fixclient/http_client/event_loop_thread.py
fixclient/json_utils.py
fixclient/jwt_utils.py
fixclient/models.py
fixclient-2.0.0.dist-info/LICENSE
fixclient-2.0.0.dist-info/METADATA
fixclient-2.0.0.dist-info/WHEEL
fixclient-2.0.0.dist-info/RECORD
